py_thanos_snap-0.1.4.dist-info/licenses/LICENSE
thanospy/__init__.py
thanospy/core.py
py_thanos_snap-0.1.4.dist-info/METADATA
py_thanos_snap-0.1.4.dist-info/WHEEL
py_thanos_snap-0.1.4.dist-info/top_level.txt
py_thanos_snap-0.1.4.dist-info/RECORD
