Metadata-Version: 2.4
Name: py-thanos-snap
Version: 0.1.4
Summary: Randomly remove half the content of Python data structures, like a Thanos snap.
Author-email: Richard Chan <richard.mychan@gmail.com>
License: MIT
Project-URL: Homepage, https://github.com/manyan-chan/thanosPy
Project-URL: Repository, https://github.com/manyan-chan/thanosPy
Keywords: thanos,snap,random,sample,reduce,list,dict,set,data structure,half
Classifier: Programming Language :: Python :: 3
Classifier: Programming Language :: Python :: 3.8
Classifier: Programming Language :: Python :: 3.9
Classifier: Programming Language :: Python :: 3.10
Classifier: Programming Language :: Python :: 3.11
Classifier: Programming Language :: Python :: 3.12
Classifier: License :: OSI Approved :: MIT License
Classifier: Operating System :: OS Independent
Classifier: Development Status :: 4 - Beta
Classifier: Intended Audience :: Developers
Classifier: Intended Audience :: Science/Research
Classifier: Topic :: Software Development :: Libraries :: Python Modules
Classifier: Topic :: Utilities
Classifier: Topic :: Scientific/Engineering :: Information Analysis
Classifier: Typing :: Typed
Requires-Python: >=3.8
License-File: LICENSE
Provides-Extra: test
Requires-Dist: pytest>=7.0; extra == "test"
Requires-Dist: pytest-cov; extra == "test"
Dynamic: license-file
